deadline/houdini_adaptor/__init__.py
deadline/houdini_adaptor/_version.py
deadline/houdini_adaptor/HoudiniAdaptor/HoudiniAdaptor.json
deadline/houdini_adaptor/HoudiniAdaptor/__init__.py
deadline/houdini_adaptor/HoudiniAdaptor/__main__.py
deadline/houdini_adaptor/HoudiniAdaptor/adaptor.py
deadline/houdini_adaptor/HoudiniAdaptor/schemas/init_data.schema.json
deadline/houdini_adaptor/HoudiniAdaptor/schemas/run_data.schema.json
deadline/houdini_adaptor/HoudiniClient/__init__.py
deadline/houdini_adaptor/HoudiniClient/houdini_client.py
deadline/houdini_adaptor/HoudiniClient/houdini_handler.py
deadline/houdini_submitter/_version.py
deadline/houdini_submitter/otls/deadline_cloud.hda/INDEX__SECTION
deadline/houdini_submitter/otls/deadline_cloud.hda/Sections.list
deadline/houdini_submitter/otls/deadline_cloud.hda/houdini.hdalibrary
deadline/houdini_submitter/otls/deadline_cloud.hda/Driver_1deadline__cloud/CreateScript
deadline/houdini_submitter/otls/deadline_cloud.hda/Driver_1deadline__cloud/DialogScript
deadline/houdini_submitter/otls/deadline_cloud.hda/Driver_1deadline__cloud/ExtraFileOptions
deadline/houdini_submitter/otls/deadline_cloud.hda/Driver_1deadline__cloud/Help
deadline/houdini_submitter/otls/deadline_cloud.hda/Driver_1deadline__cloud/IconSVG
deadline/houdini_submitter/otls/deadline_cloud.hda/Driver_1deadline__cloud/OnCreated
deadline/houdini_submitter/otls/deadline_cloud.hda/Driver_1deadline__cloud/PythonModule
deadline/houdini_submitter/otls/deadline_cloud.hda/Driver_1deadline__cloud/Sections.list
deadline/houdini_submitter/otls/deadline_cloud.hda/Driver_1deadline__cloud/Tools.shelf
deadline/houdini_submitter/otls/deadline_cloud.hda/Driver_1deadline__cloud/TypePropertiesOptions
deadline/houdini_submitter/python/deadline_cloud_for_houdini/__init__.py
deadline/houdini_submitter/python/deadline_cloud_for_houdini/_assets.py
deadline/houdini_submitter/python/deadline_cloud_for_houdini/_version.py
deadline_cloud_for_houdini-0.7.9.dist-info/METADATA
deadline_cloud_for_houdini-0.7.9.dist-info/WHEEL
deadline_cloud_for_houdini-0.7.9.dist-info/entry_points.txt
deadline_cloud_for_houdini-0.7.9.dist-info/licenses/LICENSE
deadline_cloud_for_houdini-0.7.9.dist-info/licenses/NOTICE
deadline_cloud_for_houdini-0.7.9.dist-info/RECORD
